Fivepaisa_modular/__init__.py
Fivepaisa_modular/auto_sqoff.py
Fivepaisa_modular/create_log.py
Fivepaisa_modular/df_strike_gen.py
Fivepaisa_modular/inputs.py
Fivepaisa_modular/login.py
Fivepaisa_modular/order_place.py
Fivepaisa_modular/pip_installs.py
Fivepaisa_modular/print.py
Fivepaisa_modular/scripmaster_download.py
Fivepaisa_modular/sl_monitoring.py
Fivepaisa_modular/stoploss_place.py
5paisa_modular-0.0.1.dist-info/LICENCE.txt
5paisa_modular-0.0.1.dist-info/METADATA
5paisa_modular-0.0.1.dist-info/WHEEL
5paisa_modular-0.0.1.dist-info/top_level.txt
5paisa_modular-0.0.1.dist-info/RECORD
